jk_ff.v
module jk_ff( input clk,reset,j,k,
output reg q);

always@(posedge clk)
begin
if(reset) begin
	q<=1'b0;
	  end

else begin
	case({j,k})
	2'b00: q<=q;
	2'b01: q<=1'b0;
	2'b10: q<=1'b1;
	2'b11: q<=~q;
	default: q<=1'b0;
	endcase
     end
end
endmodule

jk_tb.v
module jk_tb();
reg clk,reset,j,k;
wire q;

jk_ff j1(.clk(clk),.reset(reset),.j(j),.k(k),.q(q));

initial 
begin
$dumpfile("jk_test.vcd");
$dumpvars(0,jk_tb);
end

always #2 clk=~clk;

initial
begin
clk=1'b0;
reset=1'b1;
j=1'b1;
k=1'b0;

#10
reset=1'b0;
j=1'b1;
k=1'b0;
#10
j=1'b0;
k=1'b0;
#10
j=1'b0;
k=1'b1;
#10
j=1'b1;
k=1'b1;

#500 $finish;
end
endmodule

jk_test.vcd
$date
	Wed Apr 10 10:33:51 2024
$end
$version
	Icarus Verilog
$end
$timescale
	1s
$end
$scope module jk_tb $end
$var wire 1 ! q $end
$var reg 1 " clk $end
$var reg 1 # j $end
$var reg 1 $ k $end
$var reg 1 % reset $end
$scope module j1 $end
$var wire 1 " clk $end
$var wire 1 # j $end
$var wire 1 $ k $end
$var wire 1 % reset $end
$var reg 1 ! q $end
$upscope $end
$upscope $end
$enddefinitions $end
#0
$dumpvars
1%
0$
1#
0"
x!
$end
#2
0!
1"
#4
0"
#6
1"
#8
0"
#10
1!
1"
0%
#12
0"
#14
1"
#16
0"
#18
1"
#20
0"
0#
#22
1"
#24
0"
#26
1"
#28
0"
#30
0!
1"
1$
#32
0"
#34
1"
#36
0"
#38
1"
#40
0"
1#
#42
1!
1"
#44
0"
#46
0!
1"
#48
0"
#50
1!
1"
#52
0"
#54
0!
1"
#56
0"
#58
1!
1"
#60
0"
#62
0!
1"
#64
0"
#66
1!
1"
#68
0"
#70
0!
1"
#72
0"
#74
1!
1"
#76
0"
#78
0!
1"
#80
0"
#82
1!
1"
#84
0"
#86
0!
1"
#88
0"
#90
1!
1"
#92
0"
#94
0!
1"
#96
0"
#98
1!
1"
#100
0"
#102
0!
1"
#104
0"
#106
1!
1"
#108
0"
#110
0!
1"
#112
0"
#114
1!
1"
#116
0"
#118
0!
1"
#120
0"
#122
1!
1"
#124
0"
#126
0!
1"
#128
0"
#130
1!
1"
#132
0"
#134
0!
1"
#136
0"
#138
1!
1"
#140
0"
#142
0!
1"
#144
0"
#146
1!
1"
#148
0"
#150
0!
1"
#152
0"
#154
1!
1"
#156
0"
#158
0!
1"
#160
0"
#162
1!
1"
#164
0"
#166
0!
1"
#168
0"
#170
1!
1"
#172
0"
#174
0!
1"
#176
0"
#178
1!
1"
#180
0"
#182
0!
1"
#184
0"
#186
1!
1"
#188
0"
#190
0!
1"
#192
0"
#194
1!
1"
#196
0"
#198
0!
1"
#200
0"
#202
1!
1"
#204
0"
#206
0!
1"
#208
0"
#210
1!
1"
#212
0"
#214
0!
1"
#216
0"
#218
1!
1"
#220
0"
#222
0!
1"
#224
0"
#226
1!
1"
#228
0"
#230
0!
1"
#232
0"
#234
1!
1"
#236
0"
#238
0!
1"
#240
0"
#242
1!
1"
#244
0"
#246
0!
1"
#248
0"
#250
1!
1"
#252
0"
#254
0!
1"
#256
0"
#258
1!
1"
#260
0"
#262
0!
1"
#264
0"
#266
1!
1"
#268
0"
#270
0!
1"
#272
0"
#274
1!
1"
#276
0"
#278
0!
1"
#280
0"
#282
1!
1"
#284
0"
#286
0!
1"
#288
0"
#290
1!
1"
#292
0"
#294
0!
1"
#296
0"
#298
1!
1"
#300
0"
#302
0!
1"
#304
0"
#306
1!
1"
#308
0"
#310
0!
1"
#312
0"
#314
1!
1"
#316
0"
#318
0!
1"
#320
0"
#322
1!
1"
#324
0"
#326
0!
1"
#328
0"
#330
1!
1"
#332
0"
#334
0!
1"
#336
0"
#338
1!
1"
#340
0"
#342
0!
1"
#344
0"
#346
1!
1"
#348
0"
#350
0!
1"
#352
0"
#354
1!
1"
#356
0"
#358
0!
1"
#360
0"
#362
1!
1"
#364
0"
#366
0!
1"
#368
0"
#370
1!
1"
#372
0"
#374
0!
1"
#376
0"
#378
1!
1"
#380
0"
#382
0!
1"
#384
0"
#386
1!
1"
#388
0"
#390
0!
1"
#392
0"
#394
1!
1"
#396
0"
#398
0!
1"
#400
0"
#402
1!
1"
#404
0"
#406
0!
1"
#408
0"
#410
1!
1"
#412
0"
#414
0!
1"
#416
0"
#418
1!
1"
#420
0"
#422
0!
1"
#424
0"
#426
1!
1"
#428
0"
#430
0!
1"
#432
0"
#434
1!
1"
#436
0"
#438
0!
1"
#440
0"
#442
1!
1"
#444
0"
#446
0!
1"
#448
0"
#450
1!
1"
#452
0"
#454
0!
1"
#456
0"
#458
1!
1"
#460
0"
#462
0!
1"
#464
0"
#466
1!
1"
#468
0"
#470
0!
1"
#472
0"
#474
1!
1"
#476
0"
#478
0!
1"
#480
0"
#482
1!
1"
#484
0"
#486
0!
1"
#488
0"
#490
1!
1"
#492
0"
#494
0!
1"
#496
0"
#498
1!
1"
#500
0"
#502
0!
1"
#504
0"
#506
1!
1"
#508
0"
#510
0!
1"
#512
0"
#514
1!
1"
#516
0"
#518
0!
1"
#520
0"
#522
1!
1"
#524
0"
#526
0!
1"
#528
0"
#530
1!
1"
#532
0"
#534
0!
1"
#536
0"
#538
1!
1"
